fastapi_initializer/__init__.py
fastapi_initializer/fastapi_initializer.py
fastapi_project_initializer/__init__.py
fastapi_project_initializer/main.py
fastapi_project_initializer-0.1.4.dist-info/METADATA
fastapi_project_initializer-0.1.4.dist-info/WHEEL
fastapi_project_initializer-0.1.4.dist-info/entry_points.txt
fastapi_project_initializer-0.1.4.dist-info/top_level.txt
fastapi_project_initializer-0.1.4.dist-info/RECORD
