Metadata-Version: 2.1
Name: fastapi_project_initializer
Version: 0.1.4
Summary: A library to initialize a FastAPI project
Home-page: https://github.com/kmarov17/fastapi_project_initializer.git
Author: Kodana Diarra aka(kmarov)
Author-email: kodanadiarra@gmail.com
Classifier: Programming Language :: Python :: 3
Classifier: License :: OSI Approved :: MIT License
Classifier: Operating System :: OS Independent
Requires-Python: >=3.6
Requires-Dist: gitpython
